{"head":{"version":"1.1.0","author":"听雨荷","course":"学习通","filename":"基本检查法、一般状况检查实验作业","type_all_num":25,"time":"25年03月14日10小时39分38秒","id":"id-m8866hui-dnul3bfcz"},"body":[{"questions":"呕吐物有粪臭味见于( )","options":[" 肠梗阻"," 有机磷中毒"," 幽门梗阻"," 糖尿病酮症酸中毒"," 肺脓肿"],"type":"单选题","type_code":1,"answers":"A","answers_matching_index":[0],"analysis":[]},{"questions":"触诊对全身的哪个部位的检查更重要","options":[" 皮肤"," 腹部"," 胸部"," 颈部"],"type":"单选题","type_code":1,"answers":"B","answers_matching_index":[1],"analysis":[]},{"questions":"下述各项不正确者为:","options":[" 超过标准体重20%以上者为肥胖"," 低于标准体重10%以上者为消瘦"," 坐高等于下肢长度"," 正常人腹上角大于90度"," 两上肢展开的长度约等于身高"],"type":"单选题","type_code":1,"answers":"D","answers_matching_index":[3],"analysis":[]},{"questions":"乳腺炎时可出现哪组淋巴结肿大？","options":[" 腋窝淋巴结"," 腹股沟淋巴结"," 右锁骨上淋巴结"," 左锁骨上淋巴结"," 滑车上淋巴结"],"type":"单选题","type_code":1,"answers":"A","answers_matching_index":[0],"analysis":[]},{"questions":"关于蜘蛛痣不正确的是:","options":[" 大多在上腔静脉分布区域"," 与肝对体内雌激素的灭活减弱有关"," 肝掌的发生机制与蜘蛛痣相同"," 常见于肝病患者"," 均属病理性"],"type":"单选题","type_code":1,"answers":"E","answers_matching_index":[4],"analysis":[]},{"questions":"呼吸有烂苹果味常见于","options":[" 有机磷农药中毒"," 糖尿病酮症酸中毒"," 酒精中毒"," 肝昏迷"," 尿毒症"],"type":"单选题","type_code":1,"answers":"B","answers_matching_index":[1],"analysis":[]},{"questions":"呼吸气有烂苹果味见于( )","options":[" 肺脓肿"," 有机磷中毒"," 肠梗阻"," 幽门梗阻"," 糖尿病酮症酸中毒"],"type":"单选题","type_code":1,"answers":"E","answers_matching_index":[4],"analysis":[]},{"questions":"贫血时皮肤、粘膜苍白。较可靠的检查部位是:\n\n\n\n\n\n","options":[" 颈部皮肤及舌面"," 面颊皮肤及上腭粘膜"," 手背皮肤及鼻腔粘膜"," 手掌皮肤及睑结膜"," 耳廓皮肤及上腭粘膜"],"type":"单选题","type_code":1,"answers":"D","answers_matching_index":[3],"analysis":[]},{"questions":"痰液有恶臭味见于( )","options":[" 糖尿病酮症酸中毒"," 有机磷中毒"," 肺脓肿"," 幽门梗阻"," 肠梗阻"],"type":"单选题","type_code":1,"answers":"C","answers_matching_index":[2],"analysis":[]},{"questions":"触诊腹肌有无抵抗感,首选触诊方法为","options":[" 深部双手触诊法"," 深部深压触诊法"," 滑动触诊法"," 浅部触诊法"," 深部冲击触诊法"],"type":"单选题","type_code":1,"answers":"D","answers_matching_index":[3],"analysis":[]},{"questions":"关于深部滑行触诊法下述哪项错误?","options":[" 并拢二、三、四指末端逐渐触及腹腔的脏器或包块"," 适用于腹腔深部包块和胃肠病变的检查"," 在被触及的脏器或包块上作上下左右滑动触摸"," 嘱患者张口平静呼吸,尽量使腹肌松弛"," 如为肠管,则须作与长轴相平行方向的滑动触摸"],"type":"单选题","type_code":1,"answers":"E","answers_matching_index":[4],"analysis":[]},{"questions":"乳腺炎时可出现哪组淋巴结肿大?","options":[" 腋窝淋巴结"," 右锁骨上淋巴结"," 腹股沟淋巴结"," 左锁骨上淋巴结"," 滑车上淋巴结"],"type":"单选题","type_code":1,"answers":"A","answers_matching_index":[0],"analysis":[]},{"questions":"判断营养状态最准确而迅速的方法是","options":[" 体格发育"," 毛发的分布及色泽"," 察看皮下脂肪充实的程度"," 肌肉的发育状态"," 皮肤情况"],"type":"单选题","type_code":1,"answers":"C","answers_matching_index":[2],"analysis":[]},{"questions":"女性雌激素的作用不包括下述哪顶?","options":[" 腋毛和阴毛过多"," 外阴的发育"," 卵巢的发育"," 子宫的发育"," 乳房发育"],"type":"单选题","type_code":1,"answers":"A","answers_matching_index":[0],"analysis":[]},{"questions":"触诊可以补充","options":[" 嗅诊所不能确定的体征;"," 问诊不能确定的体征。"," 听诊所不能确定的体征;"," 视诊所不能确定的体征;"," 叩诊所不能确定的体征"],"type":"单选题","type_code":1,"answers":"D","answers_matching_index":[3],"analysis":[]},{"questions":"大量胸腔积液时可以用下列那种方法检查","options":[" 两者均否"," 间接叩诊法"," 直接叩诊法"," 两者均可"],"type":"单选题","type_code":1,"answers":"D","answers_matching_index":[3],"analysis":[]},{"questions":"声音嘶哑见于","options":[" 喉癌"," 喉部炎症"," 喉结核"," 急性扁桃体炎"," 喉返神经麻痹"],"type":"多选题","type_code":2,"answers":"ABCE","answers_matching_index":[0,1,2,4],"analysis":[]},{"questions":"体温低于正常称体温过低,见于","options":[" 严重营养不良"," 慢性消耗性疾病"," 甲状腺功能低下"," 休克"," 在低温环境中暴露过久"],"type":"多选题","type_code":2,"answers":"ABCDE","answers_matching_index":[0,1,2,3,4],"analysis":[]},{"questions":"面部呆板,无表情,似面具面容,可见于","options":[" 破伤风"," 脑萎缩"," 震颤性麻痹"," 脑炎"," 脑血管疾病"],"type":"多选题","type_code":2,"answers":"CD","answers_matching_index":[2,3],"analysis":[]},{"questions":"体格检查的基本检查方法有哪几种?","options":[" 触诊"," 听诊"," 视诊"," 嗅诊"," 叩诊"],"type":"多选题","type_code":2,"answers":"ABCDE","answers_matching_index":[0,1,2,3,4],"analysis":[]},{"questions":"全身性淋巴结肿大可见于","options":[" 再生障碍性贫血"," 淋巴瘤"," 急、慢性淋巴结炎"," 传染性单核细胞增多症"," 慢性白血病"],"type":"多选题","type_code":2,"answers":"BCDE","answers_matching_index":[1,2,3,4],"analysis":[]},{"questions":"表情淡漠,反应迟钝,呈无欲状态的面容常见于","options":[" 肠伤寒"," 脑脊髓膜炎"," 破伤风"," 肺结核"," 脑炎"],"type":"多选题","type_code":2,"answers":"ABE","answers_matching_index":[0,1,4],"analysis":[]},{"questions":"下列哪些疾病多见于幼儿及儿童","options":[" 风湿热"," 麻疹"," 佝偻病"," 动脉硬化"," 白喉"],"type":"多选题","type_code":2,"answers":"BCE","answers_matching_index":[1,2,4],"analysis":[]},{"questions":"醉酒步态可见于","options":[" 酒精中毒"," 进行性肌营养不良"," 巴比妥中毒"," 小脑疾病"," 高血压、动脉硬化"],"type":"多选题","type_code":2,"answers":"ACD","answers_matching_index":[0,2,3],"analysis":[]},{"questions":"根据音响的强弱、频率等的不同将正常和病理性叩诊音分为____、____、____、____和____五种。","options":[],"type":"填空题","type_code":4,"answers":[" 清音"," 鼓音"," 过清音"," 浊音"," 实音"],"answers_matching_index":[],"analysis":[]}]}