[
    {
        "name": "神经系统1.json",
        "path": [
            ".\/json\/大二上 生理学B\/神经系统1.json"
        ]
    },
    {
        "name": "第一章 绪论.json",
        "path": [
            ".\/json\/大二上 生理学B\/第一章 绪论.json"
        ]
    },
    {
        "name": "第七章 泌尿（尿液生成和排出）.json",
        "path": [
            ".\/json\/大二上 生理学B\/第七章 泌尿（尿液生成和排出）.json"
        ]
    },
    {
        "name": "第三章 血液.json",
        "path": [
            ".\/json\/大二上 生理学B\/第三章 血液.json"
        ]
    },
    {
        "name": "第二章 细胞基本功能.json",
        "path": [
            ".\/json\/大二上 生理学B\/第二章 细胞基本功能.json"
        ]
    },
    {
        "name": "第五章 呼吸.json",
        "path": [
            ".\/json\/大二上 生理学B\/第五章 呼吸.json"
        ]
    },
    {
        "name": "第八章 神经系统.json",
        "path": [
            ".\/json\/大二上 生理学B\/第八章 神经系统.json"
        ]
    },
    {
        "name": "第六章 消化和吸收.json",
        "path": [
            ".\/json\/大二上 生理学B\/第六章 消化和吸收.json"
        ]
    },
    {
        "name": "第四章 血液循环.json",
        "path": [
            ".\/json\/大二上 生理学B\/第四章 血液循环.json"
        ]
    }
]