{"head":{"version":"1.1.0","author":"听雨荷","course":"学习通","filename":"《保障粮食安全的中国策》专题作业","type_all_num":40,"time":"25年01月09日12小时48分29秒","id":"id-m5oulobn-a9q4fa0cm"},"body":[{"questions":"(单选题, 2分)作为农业的芯片,( )是保障粮食安全的关键。","options":[" 农业"," 种子"," 乡村"," 土地"],"type":"单选题","type_code":1,"answers":" B","answers_matching_index":[1],"analysis":[]},{"questions":"(单选题, 2分)世界粮农组织将( )作为衡量全球或一个国家粮食安全程度的重要标准。","options":[" 库存消费比"," 粮食产量"," 粮食库存量"," 粮食加工转化量"],"type":"单选题","type_code":1,"answers":" B","answers_matching_index":[1],"analysis":[]},{"questions":"(单选题, 2分)( )重点提升粮食生产能力,依托大粮仓打造粮肉奶综合供应基站。","options":[" 东北地区"," 华北地区"," 华南地区"," 长江中下游地区"],"type":"单选题","type_code":1,"answers":" A","answers_matching_index":[0],"analysis":[]},{"questions":"(单选题, 2分)在历史上第一次提出了“民以食为天”民生思想的,是春秋时期齐国著名的政治家( )。","options":[" 荀子"," 孟子"," 管仲"," 孔子"],"type":"单选题","type_code":1,"answers":" C","answers_matching_index":[2],"analysis":[]},{"questions":"(单选题, 2分)每年农历( )为中国农民丰收节。","options":[" 春分"," 夏至"," 立秋"," 秋分"],"type":"单选题","type_code":1,"answers":" D","answers_matching_index":[3],"analysis":[]},{"questions":"(单选题, 2分)土地承包期限目前最长是(    )年。","options":[" 15"," 30"," 45"," 70"],"type":"单选题","type_code":1,"answers":" D","answers_matching_index":[3],"analysis":[]},{"questions":"(单选题, 2分)袁隆平先生是享誉海内外的著名农业科学家,中国杂交水稻事业的开创者和领导者,“共和国勋章”获得者,致力于杂交水稻技术的研究、应用与推广,发明“三系法”籼型杂交水稻,成功研究出“两系法”杂交水稻,创建了超级杂交稻技术体系,被誉为( )。","options":[" 杂交水稻之父"," 中国当代农学家"," 杂交水稻育种专家"," 超级稻专家"],"type":"单选题","type_code":1,"answers":" A","answers_matching_index":[0],"analysis":[]},{"questions":"(单选题, 2分)历来政治家治国安邦的第一要义是( )。","options":[" 保障粮食安全"," 三农思想"," 农业是国民经济的基础"," 民以食为天"],"type":"单选题","type_code":1,"answers":" D","answers_matching_index":[3],"analysis":[]},{"questions":"(单选题, 2分)反对餐饮浪费,是中华民族的优良传统,也是新时代消费风尚。节约粮食的关键一环是( )。","options":[" 减少粮食损失"," 培养人们的节约意识"," 杜绝消费环节“舌尖上的浪费”"," 加大各大网络媒体的宣传力度"],"type":"单选题","type_code":1,"answers":" C","answers_matching_index":[2],"analysis":[]},{"questions":"(单选题, 2分)农业在我国的地位是( )","options":[" 支柱产业"," 重要产业"," 主要产业"," 基础产业"],"type":"单选题","type_code":1,"answers":" D","answers_matching_index":[3],"analysis":[]},{"questions":"(单选题, 2分)我国在粮食流通领域出台的主要法律法规是( )。","options":[" 《中央储备粮管理条例》"," 《粮食流通管理条例》"," 《粮油储藏技术规范》"," 《粮油仓储管理办法》"],"type":"单选题","type_code":1,"answers":" B","answers_matching_index":[1],"analysis":[]},{"questions":"(单选题, 2分)当粮食供求关系发生重大变化时,为保障供市场供应,保护种粮农民利益,必要时可由国务院决定对短缺的重点粮食品种在粮食主产区实行( )。","options":[" 最低收购价"," 市场价"," 浮动价格"," 最高限价"],"type":"单选题","type_code":1,"answers":" A","answers_matching_index":[0],"analysis":[]},{"questions":"(单选题, 2分)对农民来说,土地是“命根子”,是生存权益最集中的体现。下列哪一部法律指出:要废除地主阶级封建剥削的土地所有制,实行农民的土地所有制,借以解放农村生产力,发展农业生产,为新中国的工业化开辟道路。( )","options":[" 《中华人民共和国土地改革法》"," 《中国土地法大纲》"," 《关于清算减租及土地问题的指示》"," 《井冈山土地法》"],"type":"单选题","type_code":1,"answers":" A","answers_matching_index":[0],"analysis":[]},{"questions":"(单选题, 2分)深入实施藏粮于地、藏粮于技战略,落实最严格的( )保护机制。","options":[" 生态"," 湿地"," 耕地"," 水源"],"type":"单选题","type_code":1,"answers":" C","answers_matching_index":[2],"analysis":[]},{"questions":"(单选题, 2分)( )是农业的核心竞争力。","options":[" 种业"," 科技"," 人才"," 创新"],"type":"单选题","type_code":1,"answers":" A","answers_matching_index":[0],"analysis":[]},{"questions":"(单选题, 2分)粮食安全是国家安全的重要基础,确保粮食安全始终是治国理政的头等大事。五谷者,万民之命,国之重宝,中国人的饭碗任何时候都要端在自己手中。以下哪一个选项是人类生存和发展的首要问题( )。","options":[" 交通出行"," 基础设施"," 吃饭问题"," 文化交流"],"type":"单选题","type_code":1,"answers":" C","answers_matching_index":[2],"analysis":[]},{"questions":"(单选题, 2分)保障粮食安全的内涵不断拓宽,现如今人们更加注重食品安全、营养和均衡。下列有关食品安全的表述正确的是( )。","options":[" 经过高温灭菌过程,食品中不含有任何致病微生物。"," 食品无毒、无害,符合应当有的营养要求,对人体健康不造成任何急性、亚急性或者慢性危害。"," 原料天然,食品中不含有任何人工合成物质。"," 虽然过了保质期,但外观、口感正常。"],"type":"单选题","type_code":1,"answers":" B","answers_matching_index":[1],"analysis":[]},{"questions":"(单选题, 2分)1978年初冬的一个黄昏,18位农民聚集在村民严立华的家中,冒着坐牢杀头的风险,提出了“分田单干”“包产到户”的想法,带着“托孤”的决心商量到深夜,18位农民以“敢为天下先”的胆识在这张契约上按下了自己的红手印,按出一道改革惊雷,搞起了“大包干”。本身几个农民按手印是解决温饱问题,但是却意外地擦亮一根火柴,点燃了中国大地的农村改革,解决了中国亿万农民的温饱问题,是中国农村改革史上的一面旗帜,引领着中国农村土地制度的改革。以上描述的中国农村改革发生在( )。","options":[" 安徽省凤阳县小岗村"," 江苏省江阴市华西村"," 河南省临颍县南街村"," 山西省昔阳县大寨村"],"type":"单选题","type_code":1,"answers":" A","answers_matching_index":[0],"analysis":[]},{"questions":"(单选题, 2分)党深化推进农村土地制度改革,完善承包地“三权”分置制度,“三权”不包括( )。","options":[" 所有权"," 承包权"," 经营权"," 治理权"],"type":"单选题","type_code":1,"answers":" D","answers_matching_index":[3],"analysis":[]},{"questions":"(单选题, 2分)十年来,我国坚持并落实最严格的耕地保护制度,严格划定并守住了耕地保护红线,其中耕地保护红线是( )亿亩。","options":[" 10"," 15"," 18"," 25"],"type":"单选题","type_code":1,"answers":" C","answers_matching_index":[2],"analysis":[]},{"questions":"(多选题, 4分)我国是天然缺水大国,淡水资源总量仅占全球6%,被联合国列为13个贫水国家之一,气候特征决定了我国农业在很大程度上依赖灌溉。下列对于喷灌的优点描述正确的是( )。","options":[" 节约水资源"," 不破坏土壤结构"," 不受地形限制"," 设备成本较高"],"type":"多选题","type_code":2,"answers":" ABC","answers_matching_index":[0,1,2],"analysis":[]},{"questions":"(多选题, 4分)中央和地方必须扛起粮食安全的政治责任,实行党政同责。国家加强对粮食市场宏观调控的手段有( )。","options":[" 储备粮吞吐"," 委托收购"," 价格干预"," 粮食进出口"],"type":"多选题","type_code":2,"answers":" ABCD","answers_matching_index":[0,1,2,3],"analysis":[]},{"questions":"(多选题, 4分)2022年5月20日是第33届中国学生营养日,今年的主题是( )。","options":[" 知营养"," 会运动"," 防肥胖"," 促健康"],"type":"多选题","type_code":2,"answers":" ABCD","answers_matching_index":[0,1,2,3],"analysis":[]},{"questions":"(多选题, 4分)为落实党中央、国务院关于耕地数量管控、质量管理和生态管护的有关要求,进一步丰富耕地保护内涵,提升耕地保护水平,全面加强耕地质量建设与管理工作,以下表述正确的有( )。","options":[" 加快划定永久基本农田,严格管控优质耕地"," 大力推进农村土地整治,全面提升耕地质量等级"," 严格落实耕地占补平衡,把好补充耕地质量关"," 持续加强监测评价,及时掌握耕地质量动态变化"],"type":"多选题","type_code":2,"answers":" ABCD","answers_matching_index":[0,1,2,3],"analysis":[]},{"questions":"(多选题, 4分)我国粮食储备率大大超过联合国粮农组织规定的17%~18%的安全储备率水平,特别是两大口粮的储备量够全国人民吃一年。其中两大口粮是指( )。","options":[" 玉米"," 小麦"," 大豆"," 稻谷"],"type":"多选题","type_code":2,"answers":" BD","answers_matching_index":[1,3],"analysis":[]},{"questions":"(多选题, 4分)“一多三少”是我国耕地的基本现状,以下对于“三少”的描述正确的有( )。","options":[" 人均占有量少"," 优质的耕地少"," 淡水资源总量少"," 耕地的后备资源少"],"type":"多选题","type_code":2,"answers":" ABD","answers_matching_index":[0,1,3],"analysis":[]},{"questions":"(多选题, 4分)为缓解我国副食品供应偏紧的矛盾,农业部于1988年提出建设“菜篮子工程”。“菜篮子”产品持续快速增长,从根本上扭转了我国副食品供应长期短缺的局面。除奶类和水果外,其余“菜篮子”产品的人均占有量均已达到或超过世界人均水平。下列描述菜篮子工程成果正确的为( )。","options":[" 农产品的产量增长,品种日趋丰富,质量不断改善,中国城镇副食品供应长期短缺局面已经结束。"," 各大中城市经过反复和艰难的探索,成功地建立起了市场化的产销运行制度。"," “菜篮子”生产逐步成为大中城市郊区和部分农区农业发展的支柱产业,成为增加农民收入的重要来源。"," “菜篮子”产品供给状况的改观,特别是“菜篮子”产品价格涨幅的明显回落,有效地缓解了国民经济运行中的通货膨胀压力。"],"type":"多选题","type_code":2,"answers":" ABCD","answers_matching_index":[0,1,2,3],"analysis":[]},{"questions":"(多选题, 4分)下列关于节约粮食的做法正确的是( )。","options":[" 按量取餐"," 习惯打包"," 光盘行动"," 杜绝攀比"],"type":"多选题","type_code":2,"answers":" ABCD","answers_matching_index":[0,1,2,3],"analysis":[]},{"questions":"(多选题, 4分)中国古代所称的“五谷”指的是( )。","options":[" 麦,黍"," 稻,菽"," 稷"," 豆"],"type":"多选题","type_code":2,"answers":" ABC","answers_matching_index":[0,1,2],"analysis":[]},{"questions":"(多选题, 4分)粮食消费观是粮食精神文化的重要组成部分,对粮食消费起引导作用的是( )。","options":[" 价值取向"," 生活理念"," 审美意识"," 平抑市场粮价"],"type":"多选题","type_code":2,"answers":" AB","answers_matching_index":[0,1],"analysis":[]},{"questions":"(判断题, 2分)我国的主要粮食作物为稻谷,小麦,玉米,大豆,其中稻谷是我国第二大粮食作物。( )","options":["错误","正确"],"type":"判断题","type_code":3,"answers":": 错","answers_matching_index":[0],"analysis":[]},{"questions":"(判断题, 2分)小麦是现今世界上最主要的粮食作物,在我国栽培历史已有5000多年。( )","options":["错误","正确"],"type":"判断题","type_code":3,"answers":": 对","answers_matching_index":[1],"analysis":[]},{"questions":"(判断题, 2分)当市场粮价低于国家确定的最低收购价时,国家委托符合一定资质条件的粮食企业,按国家确定的最低收购价收购农民的粮食。( )","options":["错误","正确"],"type":"判断题","type_code":3,"answers":": 对","answers_matching_index":[1],"analysis":[]},{"questions":"(判断题, 2分)大食物观就是要转变食物结构,既要向耕地要粮食,又要从耕地资源向整个国土资源拓展。( )","options":["错误","正确"],"type":"判断题","type_code":3,"answers":": 对","answers_matching_index":[1],"analysis":[]},{"questions":"(判断题, 2分)我国农产品及食品进口高度集中于副食品及大豆等主要饲料原料,且进口来源地、进口通道较为集中,易被“卡脖子”。( )","options":["错误","正确"],"type":"判断题","type_code":3,"answers":": 对","answers_matching_index":[1],"analysis":[]},{"questions":"(判断题, 2分)随着全球气候变暖,我国极端天气事件发生的机率增加,而且气象灾害对粮食生产的影响,虽年际间有波动,但总体呈加重趋势。( )","options":["错误","正确"],"type":"判断题","type_code":3,"answers":": 对","answers_matching_index":[1],"analysis":[]},{"questions":"(判断题, 2分)我国的大豆目前对外依存度依然超过80%。( )","options":["错误","正确"],"type":"判断题","type_code":3,"answers":": 对","answers_matching_index":[1],"analysis":[]},{"questions":"(判断题, 2分)新中国成立初期,我国保障粮食安全的目标在注重产量的同时兼顾了质量和效益。( )","options":["错误","正确"],"type":"判断题","type_code":3,"answers":": 错","answers_matching_index":[0],"analysis":[]},{"questions":"(判断题, 2分)我国谷物基本自给和口粮绝对安全的强大基础已经形成。( )","options":["错误","正确"],"type":"判断题","type_code":3,"answers":": 对","answers_matching_index":[1],"analysis":[]},{"questions":"(判断题, 2分)谷贱伤农经济学原理是指粮食获得丰收不仅不能使农民从中获益,反而还会因为粮食价格的下降而导致收入降低,用经济学原理解释,根本原因在于农产品往往是缺乏需求价格弹性的商品。( )","options":["错误","正确"],"type":"判断题","type_code":3,"answers":": 对","answers_matching_index":[1],"analysis":[]}]}